prlps_fakeua/__init__.py
prlps_fakeua/browsers.json
prlps_fakeua/fakeua.py
prlps_fakeua-0.0.1.dist-info/LICENSE.txt
prlps_fakeua-0.0.1.dist-info/METADATA
prlps_fakeua-0.0.1.dist-info/WHEEL
prlps_fakeua-0.0.1.dist-info/top_level.txt
prlps_fakeua-0.0.1.dist-info/RECORD
