Metadata-Version: 2.1
Name: prlps_fakeua
Version: 0.0.1
Summary: генерация заголовков браузеров и user-agent
Home-page: https://github.com/gniloyprolaps/fakeua
Author: prolapser
License: LICENSE.txt
Classifier: Development Status :: 4 - Beta
Classifier: Intended Audience :: Developers
Classifier: License :: OSI Approved :: MIT License
Classifier: Operating System :: OS Independent
Requires-Python: >=3.10
License-File: LICENSE.txt
Requires-Dist: httpx
